{"summary": [{"name": "Michael P. Ross", "votes": 2035, "percent": 76.1}], "precincts": [{"ward": 3, "precinct": 5, "votes_cast": 233, "candidates": [{"name": "Michael P. Ross", "votes": 227, "percent": 79.65}]}, {"ward": 4, "precinct": 6, "votes_cast": 141, "candidates": [{"name": "Michael P. Ross", "votes": 137, "percent": 83.54}]}, {"ward": 4, "precinct": 7, "votes_cast": 87, "candidates": [{"name": "Michael P. Ross", "votes": 82, "percent": 62.12}]}, {"ward": 4, "precinct": 10, "votes_cast": 7, "candidates": [{"name": "Michael P. Ross", "votes": 7, "percent": 77.78}]}, {"ward": 5, "precinct": 2, "votes_cast": 113, "candidates": [{"name": "Michael P. Ross", "votes": 109, "percent": 71.71}]}, {"ward": 5, "precinct": 3, "votes_cast": 103, "candidates": [{"name": "Michael P. Ross", "votes": 100, "percent": 72.99}]}, {"ward": 5, "precinct": 4, "votes_cast": 103, "candidates": [{"name": "Michael P. Ross", "votes": 99, "percent": 75.57}]}, {"ward": 5, "precinct": 5, "votes_cast": 59, "candidates": [{"name": "Michael P. Ross", "votes": 56, "percent": 70.0}]}, {"ward": 5, "precinct": 6, "votes_cast": 67, "candidates": [{"name": "Michael P. Ross", "votes": 66, "percent": 71.74}]}, {"ward": 5, "precinct": 7, "votes_cast": 98, "candidates": [{"name": "Michael P. Ross", "votes": 96, "percent": 78.05}]}, {"ward": 5, "precinct": 8, "votes_cast": 106, "candidates": [{"name": "Michael P. Ross", "votes": 103, "percent": 76.87}]}, {"ward": 5, "precinct": 9, "votes_cast": 83, "candidates": [{"name": "Michael P. Ross", "votes": 81, "percent": 78.64}]}, {"ward": 5, "precinct": 10, "votes_cast": 85, "candidates": [{"name": "Michael P. Ross", "votes": 82, "percent": 76.64}]}, {"ward": 5, "precinct": 11, "votes_cast": 109, "candidates": [{"name": "Michael P. Ross", "votes": 108, "percent": 83.72}]}, {"ward": 10, "precinct": 1, "votes_cast": 63, "candidates": [{"name": "Michael P. Ross", "votes": 61, "percent": 85.92}]}, {"ward": 10, "precinct": 2, "votes_cast": 87, "candidates": [{"name": "Michael P. Ross", "votes": 83, "percent": 85.57}]}, {"ward": 10, "precinct": 3, "votes_cast": 72, "candidates": [{"name": "Michael P. Ross", "votes": 70, "percent": 80.46}]}, {"ward": 10, "precinct": 4, "votes_cast": 223, "candidates": [{"name": "Michael P. Ross", "votes": 219, "percent": 79.93}]}, {"ward": 10, "precinct": 5, "votes_cast": 99, "candidates": [{"name": "Michael P. Ross", "votes": 96, "percent": 76.8}]}, {"ward": 10, "precinct": 8, "votes_cast": 104, "candidates": [{"name": "Michael P. Ross", "votes": 102, "percent": 61.45}]}, {"ward": 21, "precinct": 1, "votes_cast": 48, "candidates": [{"name": "Michael P. Ross", "votes": 46, "percent": 65.71}]}, {"ward": 21, "precinct": 2, "votes_cast": 5, "candidates": [{"name": "Michael P. Ross", "votes": 5, "percent": 83.33}]}]}