{"summary": [{"name": "Michael P. Ross", "votes": 5331, "percent": 71.14}, {"name": "Oscar T Brookins", "votes": 981, "percent": 13.09}], "precincts": [{"ward": 3, "precinct": 5, "votes_cast": 630, "candidates": [{"name": "Michael P. Ross", "votes": 566, "percent": 75.27}, {"name": "Oscar T Brookins", "votes": 61, "percent": 8.11}]}, {"ward": 4, "precinct": 6, "votes_cast": 237, "candidates": [{"name": "Michael P. Ross", "votes": 202, "percent": 66.23}, {"name": "Oscar T Brookins", "votes": 34, "percent": 11.15}]}, {"ward": 4, "precinct": 7, "votes_cast": 226, "candidates": [{"name": "Michael P. Ross", "votes": 183, "percent": 69.85}, {"name": "Oscar T Brookins", "votes": 43, "percent": 16.41}]}, {"ward": 4, "precinct": 10, "votes_cast": 38, "candidates": [{"name": "Michael P. Ross", "votes": 30, "percent": 71.43}, {"name": "Oscar T Brookins", "votes": 8, "percent": 19.05}]}, {"ward": 5, "precinct": 2, "votes_cast": 308, "candidates": [{"name": "Michael P. Ross", "votes": 265, "percent": 70.29}, {"name": "Oscar T Brookins", "votes": 43, "percent": 11.41}]}, {"ward": 5, "precinct": 3, "votes_cast": 409, "candidates": [{"name": "Michael P. Ross", "votes": 362, "percent": 78.87}, {"name": "Oscar T Brookins", "votes": 44, "percent": 9.59}]}, {"ward": 5, "precinct": 4, "votes_cast": 344, "candidates": [{"name": "Michael P. Ross", "votes": 286, "percent": 71.86}, {"name": "Oscar T Brookins", "votes": 57, "percent": 14.32}]}, {"ward": 5, "precinct": 5, "votes_cast": 196, "candidates": [{"name": "Michael P. Ross", "votes": 170, "percent": 76.92}, {"name": "Oscar T Brookins", "votes": 25, "percent": 11.31}]}, {"ward": 5, "precinct": 6, "votes_cast": 349, "candidates": [{"name": "Michael P. Ross", "votes": 297, "percent": 70.71}, {"name": "Oscar T Brookins", "votes": 51, "percent": 12.14}]}, {"ward": 5, "precinct": 7, "votes_cast": 441, "candidates": [{"name": "Michael P. Ross", "votes": 383, "percent": 73.65}, {"name": "Oscar T Brookins", "votes": 57, "percent": 10.96}]}, {"ward": 5, "precinct": 8, "votes_cast": 411, "candidates": [{"name": "Michael P. Ross", "votes": 360, "percent": 75.31}, {"name": "Oscar T Brookins", "votes": 48, "percent": 10.04}]}, {"ward": 5, "precinct": 9, "votes_cast": 399, "candidates": [{"name": "Michael P. Ross", "votes": 339, "percent": 72.13}, {"name": "Oscar T Brookins", "votes": 58, "percent": 12.34}]}, {"ward": 5, "precinct": 10, "votes_cast": 227, "candidates": [{"name": "Michael P. Ross", "votes": 184, "percent": 64.34}, {"name": "Oscar T Brookins", "votes": 42, "percent": 14.69}]}, {"ward": 5, "precinct": 11, "votes_cast": 322, "candidates": [{"name": "Michael P. Ross", "votes": 280, "percent": 73.3}, {"name": "Oscar T Brookins", "votes": 40, "percent": 10.47}]}, {"ward": 10, "precinct": 1, "votes_cast": 186, "candidates": [{"name": "Michael P. Ross", "votes": 150, "percent": 66.08}, {"name": "Oscar T Brookins", "votes": 36, "percent": 15.86}]}, {"ward": 10, "precinct": 2, "votes_cast": 226, "candidates": [{"name": "Michael P. Ross", "votes": 180, "percent": 72.58}, {"name": "Oscar T Brookins", "votes": 46, "percent": 18.55}]}, {"ward": 10, "precinct": 3, "votes_cast": 204, "candidates": [{"name": "Michael P. Ross", "votes": 170, "percent": 76.92}, {"name": "Oscar T Brookins", "votes": 31, "percent": 14.03}]}, {"ward": 10, "precinct": 4, "votes_cast": 408, "candidates": [{"name": "Michael P. Ross", "votes": 341, "percent": 69.17}, {"name": "Oscar T Brookins", "votes": 65, "percent": 13.18}]}, {"ward": 10, "precinct": 5, "votes_cast": 263, "candidates": [{"name": "Michael P. Ross", "votes": 189, "percent": 62.17}, {"name": "Oscar T Brookins", "votes": 72, "percent": 23.68}]}, {"ward": 10, "precinct": 8, "votes_cast": 328, "candidates": [{"name": "Michael P. Ross", "votes": 254, "percent": 63.82}, {"name": "Oscar T Brookins", "votes": 74, "percent": 18.59}]}, {"ward": 21, "precinct": 1, "votes_cast": 167, "candidates": [{"name": "Michael P. Ross", "votes": 129, "percent": 62.93}, {"name": "Oscar T Brookins", "votes": 37, "percent": 18.05}]}, {"ward": 21, "precinct": 2, "votes_cast": 20, "candidates": [{"name": "Michael P. Ross", "votes": 11, "percent": 42.31}, {"name": "Oscar T Brookins", "votes": 9, "percent": 34.62}]}]}