{"summary": [{"name": "Tito Jackson", "votes": 7676, "percent": 64.83}, {"name": "Roy Owens", "votes": 1680, "percent": 14.19}, {"name": "Jamarhl C Crawford (Write-In)", "votes": 653, "percent": 5.52}], "precincts": [{"ward": 4, "precinct": 4, "votes_cast": 544, "candidates": [{"name": "Tito Jackson", "votes": 412, "percent": 59.2}, {"name": "Roy Owens", "votes": 112, "percent": 16.09}, {"name": "Jamarhl C Crawford (Write-In)", "votes": 19, "percent": 2.73}]}, {"ward": 4, "precinct": 5, "votes_cast": 362, "candidates": [{"name": "Tito Jackson", "votes": 287, "percent": 59.79}, {"name": "Roy Owens", "votes": 60, "percent": 12.5}, {"name": "Jamarhl C Crawford (Write-In)", "votes": 15, "percent": 3.12}]}, {"ward": 4, "precinct": 8, "votes_cast": 237, "candidates": [{"name": "Tito Jackson", "votes": 153, "percent": 51.17}, {"name": "Roy Owens", "votes": 76, "percent": 25.42}, {"name": "Jamarhl C Crawford (Write-In)", "votes": 5, "percent": 1.67}]}, {"ward": 4, "precinct": 9, "votes_cast": 129, "candidates": [{"name": "Tito Jackson", "votes": 95, "percent": 60.51}, {"name": "Roy Owens", "votes": 30, "percent": 19.11}, {"name": "Jamarhl C Crawford (Write-In)", "votes": 2, "percent": 1.27}]}, {"ward": 8, "precinct": 3, "votes_cast": 309, "candidates": [{"name": "Tito Jackson", "votes": 216, "percent": 66.87}, {"name": "Roy Owens", "votes": 44, "percent": 13.62}, {"name": "Jamarhl C Crawford (Write-In)", "votes": 49, "percent": 15.17}]}, {"ward": 8, "precinct": 4, "votes_cast": 189, "candidates": [{"name": "Tito Jackson", "votes": 128, "percent": 62.44}, {"name": "Roy Owens", "votes": 43, "percent": 20.98}, {"name": "Jamarhl C Crawford (Write-In)", "votes": 0, "percent": 0.0}]}, {"ward": 8, "precinct": 5, "votes_cast": 367, "candidates": [{"name": "Tito Jackson", "votes": 222, "percent": 48.47}, {"name": "Roy Owens", "votes": 115, "percent": 25.11}, {"name": "Jamarhl C Crawford (Write-In)", "votes": 30, "percent": 6.55}]}, {"ward": 8, "precinct": 7, "votes_cast": 275, "candidates": [{"name": "Tito Jackson", "votes": 180, "percent": 62.28}, {"name": "Roy Owens", "votes": 73, "percent": 25.26}, {"name": "Jamarhl C Crawford (Write-In)", "votes": 22, "percent": 7.61}]}, {"ward": 9, "precinct": 2, "votes_cast": 530, "candidates": [{"name": "Tito Jackson", "votes": 410, "percent": 58.07}, {"name": "Roy Owens", "votes": 114, "percent": 16.15}, {"name": "Jamarhl C Crawford (Write-In)", "votes": 0, "percent": 0.0}]}, {"ward": 9, "precinct": 3, "votes_cast": 721, "candidates": [{"name": "Tito Jackson", "votes": 579, "percent": 68.04}, {"name": "Roy Owens", "votes": 105, "percent": 12.34}, {"name": "Jamarhl C Crawford (Write-In)", "votes": 14, "percent": 1.65}]}, {"ward": 9, "precinct": 4, "votes_cast": 348, "candidates": [{"name": "Tito Jackson", "votes": 273, "percent": 65.78}, {"name": "Roy Owens", "votes": 52, "percent": 12.53}, {"name": "Jamarhl C Crawford (Write-In)", "votes": 23, "percent": 5.54}]}, {"ward": 9, "precinct": 5, "votes_cast": 666, "candidates": [{"name": "Tito Jackson", "votes": 484, "percent": 67.69}, {"name": "Roy Owens", "votes": 90, "percent": 12.59}, {"name": "Jamarhl C Crawford (Write-In)", "votes": 92, "percent": 12.87}]}, {"ward": 11, "precinct": 1, "votes_cast": 297, "candidates": [{"name": "Tito Jackson", "votes": 223, "percent": 69.69}, {"name": "Roy Owens", "votes": 33, "percent": 10.31}, {"name": "Jamarhl C Crawford (Write-In)", "votes": 41, "percent": 12.81}]}, {"ward": 11, "precinct": 2, "votes_cast": 457, "candidates": [{"name": "Tito Jackson", "votes": 352, "percent": 66.29}, {"name": "Roy Owens", "votes": 53, "percent": 9.98}, {"name": "Jamarhl C Crawford (Write-In)", "votes": 0, "percent": 0.0}]}, {"ward": 11, "precinct": 3, "votes_cast": 326, "candidates": [{"name": "Tito Jackson", "votes": 239, "percent": 63.56}, {"name": "Roy Owens", "votes": 46, "percent": 12.23}, {"name": "Jamarhl C Crawford (Write-In)", "votes": 0, "percent": 0.0}]}, {"ward": 12, "precinct": 1, "votes_cast": 506, "candidates": [{"name": "Tito Jackson", "votes": 374, "percent": 67.03}, {"name": "Roy Owens", "votes": 84, "percent": 15.05}, {"name": "Jamarhl C Crawford (Write-In)", "votes": 0, "percent": 0.0}]}, {"ward": 12, "precinct": 2, "votes_cast": 683, "candidates": [{"name": "Tito Jackson", "votes": 537, "percent": 70.84}, {"name": "Roy Owens", "votes": 87, "percent": 11.48}, {"name": "Jamarhl C Crawford (Write-In)", "votes": 0, "percent": 0.0}]}, {"ward": 12, "precinct": 3, "votes_cast": 365, "candidates": [{"name": "Tito Jackson", "votes": 280, "percent": 71.25}, {"name": "Roy Owens", "votes": 48, "percent": 12.21}, {"name": "Jamarhl C Crawford (Write-In)", "votes": 36, "percent": 9.16}]}, {"ward": 12, "precinct": 4, "votes_cast": 327, "candidates": [{"name": "Tito Jackson", "votes": 238, "percent": 68.59}, {"name": "Roy Owens", "votes": 41, "percent": 11.82}, {"name": "Jamarhl C Crawford (Write-In)", "votes": 48, "percent": 13.83}]}, {"ward": 12, "precinct": 5, "votes_cast": 269, "candidates": [{"name": "Tito Jackson", "votes": 218, "percent": 71.48}, {"name": "Roy Owens", "votes": 29, "percent": 9.51}, {"name": "Jamarhl C Crawford (Write-In)", "votes": 0, "percent": 0.0}]}, {"ward": 12, "precinct": 6, "votes_cast": 292, "candidates": [{"name": "Tito Jackson", "votes": 201, "percent": 64.42}, {"name": "Roy Owens", "votes": 46, "percent": 14.74}, {"name": "Jamarhl C Crawford (Write-In)", "votes": 45, "percent": 14.42}]}, {"ward": 12, "precinct": 7, "votes_cast": 685, "candidates": [{"name": "Tito Jackson", "votes": 566, "percent": 70.66}, {"name": "Roy Owens", "votes": 66, "percent": 8.24}, {"name": "Jamarhl C Crawford (Write-In)", "votes": 53, "percent": 6.62}]}, {"ward": 12, "precinct": 8, "votes_cast": 203, "candidates": [{"name": "Tito Jackson", "votes": 145, "percent": 61.44}, {"name": "Roy Owens", "votes": 23, "percent": 9.75}, {"name": "Jamarhl C Crawford (Write-In)", "votes": 35, "percent": 14.83}]}, {"ward": 12, "precinct": 9, "votes_cast": 344, "candidates": [{"name": "Tito Jackson", "votes": 251, "percent": 68.39}, {"name": "Roy Owens", "votes": 32, "percent": 8.72}, {"name": "Jamarhl C Crawford (Write-In)", "votes": 61, "percent": 16.62}]}, {"ward": 13, "precinct": 1, "votes_cast": 434, "candidates": [{"name": "Tito Jackson", "votes": 311, "percent": 64.93}, {"name": "Roy Owens", "votes": 90, "percent": 18.79}, {"name": "Jamarhl C Crawford (Write-In)", "votes": 33, "percent": 6.89}]}, {"ward": 13, "precinct": 2, "votes_cast": 164, "candidates": [{"name": "Tito Jackson", "votes": 110, "percent": 65.09}, {"name": "Roy Owens", "votes": 37, "percent": 21.89}, {"name": "Jamarhl C Crawford (Write-In)", "votes": 17, "percent": 10.06}]}, {"ward": 13, "precinct": 4, "votes_cast": 259, "candidates": [{"name": "Tito Jackson", "votes": 192, "percent": 65.31}, {"name": "Roy Owens", "votes": 51, "percent": 17.35}, {"name": "Jamarhl C Crawford (Write-In)", "votes": 13, "percent": 4.42}]}]}