{"summary": [{"name": "Matt O'Malley", "votes": 14230, "percent": 78.52}], "precincts": [{"ward": 10, "precinct": 6, "votes_cast": 204, "candidates": [{"name": "Matt O'Malley", "votes": 197, "percent": 67.01}]}, {"ward": 10, "precinct": 7, "votes_cast": 239, "candidates": [{"name": "Matt O'Malley", "votes": 237, "percent": 58.37}]}, {"ward": 10, "precinct": 8, "votes_cast": 362, "candidates": [{"name": "Matt O'Malley", "votes": 356, "percent": 72.8}]}, {"ward": 10, "precinct": 9, "votes_cast": 452, "candidates": [{"name": "Matt O'Malley", "votes": 444, "percent": 81.47}]}, {"ward": 11, "precinct": 4, "votes_cast": 395, "candidates": [{"name": "Matt O'Malley", "votes": 377, "percent": 67.44}]}, {"ward": 11, "precinct": 5, "votes_cast": 292, "candidates": [{"name": "Matt O'Malley", "votes": 284, "percent": 61.87}]}, {"ward": 11, "precinct": 6, "votes_cast": 347, "candidates": [{"name": "Matt O'Malley", "votes": 339, "percent": 76.01}]}, {"ward": 11, "precinct": 7, "votes_cast": 415, "candidates": [{"name": "Matt O'Malley", "votes": 402, "percent": 75.99}]}, {"ward": 11, "precinct": 8, "votes_cast": 480, "candidates": [{"name": "Matt O'Malley", "votes": 466, "percent": 80.07}]}, {"ward": 11, "precinct": 9, "votes_cast": 331, "candidates": [{"name": "Matt O'Malley", "votes": 322, "percent": 78.73}]}, {"ward": 11, "precinct": 10, "votes_cast": 351, "candidates": [{"name": "Matt O'Malley", "votes": 346, "percent": 77.75}]}, {"ward": 19, "precinct": 1, "votes_cast": 391, "candidates": [{"name": "Matt O'Malley", "votes": 380, "percent": 77.87}]}, {"ward": 19, "precinct": 2, "votes_cast": 522, "candidates": [{"name": "Matt O'Malley", "votes": 512, "percent": 78.77}]}, {"ward": 19, "precinct": 3, "votes_cast": 357, "candidates": [{"name": "Matt O'Malley", "votes": 352, "percent": 80.73}]}, {"ward": 19, "precinct": 4, "votes_cast": 519, "candidates": [{"name": "Matt O'Malley", "votes": 510, "percent": 80.44}]}, {"ward": 19, "precinct": 5, "votes_cast": 414, "candidates": [{"name": "Matt O'Malley", "votes": 408, "percent": 77.71}]}, {"ward": 19, "precinct": 6, "votes_cast": 612, "candidates": [{"name": "Matt O'Malley", "votes": 604, "percent": 81.4}]}, {"ward": 19, "precinct": 7, "votes_cast": 453, "candidates": [{"name": "Matt O'Malley", "votes": 445, "percent": 77.12}]}, {"ward": 19, "precinct": 8, "votes_cast": 275, "candidates": [{"name": "Matt O'Malley", "votes": 268, "percent": 80.48}]}, {"ward": 19, "precinct": 9, "votes_cast": 260, "candidates": [{"name": "Matt O'Malley", "votes": 253, "percent": 81.61}]}, {"ward": 20, "precinct": 1, "votes_cast": 431, "candidates": [{"name": "Matt O'Malley", "votes": 422, "percent": 76.31}]}, {"ward": 20, "precinct": 3, "votes_cast": 409, "candidates": [{"name": "Matt O'Malley", "votes": 399, "percent": 79.8}]}, {"ward": 20, "precinct": 5, "votes_cast": 476, "candidates": [{"name": "Matt O'Malley", "votes": 460, "percent": 78.36}]}, {"ward": 20, "precinct": 6, "votes_cast": 560, "candidates": [{"name": "Matt O'Malley", "votes": 555, "percent": 83.21}]}, {"ward": 20, "precinct": 7, "votes_cast": 362, "candidates": [{"name": "Matt O'Malley", "votes": 355, "percent": 83.92}]}, {"ward": 20, "precinct": 10, "votes_cast": 594, "candidates": [{"name": "Matt O'Malley", "votes": 590, "percent": 83.22}]}, {"ward": 20, "precinct": 11, "votes_cast": 281, "candidates": [{"name": "Matt O'Malley", "votes": 280, "percent": 83.09}]}, {"ward": 20, "precinct": 12, "votes_cast": 354, "candidates": [{"name": "Matt O'Malley", "votes": 342, "percent": 80.09}]}, {"ward": 20, "precinct": 13, "votes_cast": 322, "candidates": [{"name": "Matt O'Malley", "votes": 316, "percent": 84.27}]}, {"ward": 20, "precinct": 14, "votes_cast": 349, "candidates": [{"name": "Matt O'Malley", "votes": 341, "percent": 80.05}]}, {"ward": 20, "precinct": 15, "votes_cast": 508, "candidates": [{"name": "Matt O'Malley", "votes": 506, "percent": 83.91}]}, {"ward": 20, "precinct": 16, "votes_cast": 516, "candidates": [{"name": "Matt O'Malley", "votes": 511, "percent": 82.82}]}, {"ward": 20, "precinct": 17, "votes_cast": 586, "candidates": [{"name": "Matt O'Malley", "votes": 568, "percent": 80.8}]}, {"ward": 20, "precinct": 18, "votes_cast": 316, "candidates": [{"name": "Matt O'Malley", "votes": 310, "percent": 82.67}]}, {"ward": 20, "precinct": 19, "votes_cast": 340, "candidates": [{"name": "Matt O'Malley", "votes": 335, "percent": 82.31}]}, {"ward": 20, "precinct": 20, "votes_cast": 454, "candidates": [{"name": "Matt O'Malley", "votes": 438, "percent": 78.92}]}]}